AmpliGone/__init__.py
AmpliGone/__main__.py
AmpliGone/alignmentmatrix.py
AmpliGone/alignmentpreset.py
AmpliGone/args.py
AmpliGone/cut_reads.py
AmpliGone/cutlery.py
AmpliGone/fasta2bed.py
AmpliGone/io_ops.py
AmpliGone/log.py
ampligone-2.0.2.dist-info/METADATA
ampligone-2.0.2.dist-info/WHEEL
ampligone-2.0.2.dist-info/entry_points.txt
ampligone-2.0.2.dist-info/licenses/LICENSE
ampligone-2.0.2.dist-info/RECORD
