Metadata-Version: 2.4
Name: AmpliGone
Version: 2.0.2
Summary: AmpliGone is a tool which accurately removes primer sequences from FastQ NGS reads in an amplicon sequencing experiment
Project-URL: homepage, https://rivm-bioinformatics.github.io/AmpliGone/
Project-URL: source-code, https://github.com/RIVM-bioinformatics/AmpliGone
Author-email: Florian Zwagemaker <ids-bioinformatics@rivm.nl>
License-Expression: AGPL-3.0
License-File: LICENSE
Classifier: Development Status :: 5 - Production/Stable
Classifier: Intended Audience :: Science/Research
Classifier: Programming Language :: Python :: 3.10
Classifier: Programming Language :: Python :: 3.11
Classifier: Programming Language :: Python :: 3.12
Classifier: Topic :: Scientific/Engineering :: Bio-Informatics
Requires-Python: >=3.10
Requires-Dist: biopython==1.84
Requires-Dist: mappy==2.28
Requires-Dist: pandas==2.2.*
Requires-Dist: parasail==1.3.4
Requires-Dist: parmap==1.7.*
Requires-Dist: pgzip==0.3.4
Requires-Dist: pysam==0.22.*
Requires-Dist: rich==13.7.*
